l3/z2/twoway.vhd
library IEEE;
use IEEE.STD_LOGIC_1164.ALL;
use IEEE.numeric_std.ALL;

entity twoway is
	GENERIC (NBit : positive := 8);
   PORT ( clk : in  STD_LOGIC;
           q : out  STD_LOGIC_VECTOR (NBit-1 downto 0) 
						:= (OTHERS => '0')  -- stan power-on 
			  );
end twoway;

ARCHITECTURE Behavioral OF twoway IS
BEGIN
  PROCESS(clk)
	VARIABLE x  : UNSIGNED(NBit-1 downto 0) := (others => '0');
	VARIABLE dir: STD_LOGIC := '1';
	BEGIN
		IF (clk'event AND clk='1') THEN
			IF dir = '1' THEN
				x := x+1;
				IF x = 2 ** NBit -1 THEN 
					dir := '0';
				END IF;
			ELSE
				x := x-1;
				IF x = 0 THEN
					dir := '1';
				END IF;
			END IF;
		END IF;
		q <= STD_LOGIC_VECTOR(x);
	END PROCESS;
END Behavioral;

l3/z2/twoway_tb.vhd
LIBRARY ieee;
USE ieee.std_logic_1164.ALL;
USE ieee.numeric_std.ALL;
 
ENTITY twoway_tb IS
END twoway_tb;
 
ARCHITECTURE behavior OF twoway_tb IS 
 
    -- UUT (Unit Under Test)
    COMPONENT twoway
    PORT(
          clk  : IN  std_logic;
          q    : INOUT  STD_LOGIC_VECTOR(7 downto 0)
        );
    END COMPONENT;
    
   -- input signals
   signal clk : std_logic := '0';

   -- input/output signal
   signal qq : STD_LOGIC_VECTOR(7 downto 0);

   -- set clock period 
   constant clk_period : time := 20 ns;
 
BEGIN
	-- instantiate UUT
   uut: twoway PORT MAP (
          clk => clk,
          q   => qq
        );
   
   -- clock management process
   -- no sensitivity list, but uses 'wait'
	clk_process : process
  begin
    clk <= not clk ;
    wait for clk_period/2;
  end process;
  
  stimulate_process : process
  begin
    wait;
  end process;
END;

l3/z2/twoway.vcd
$date
  Thu Apr 22 10:41:04 2021
$end
$version
  GHDL v0
$end
$timescale
  1 fs
$end
$scope module standard $end
$upscope $end
$scope module std_logic_1164 $end
$upscope $end
$scope module numeric_std $end
$upscope $end
$scope module twoway_tb $end
$var reg 1 ! clk $end
$var reg 8 " qq[7:0] $end
$scope module uut $end
$var reg 1 # clk $end
$var reg 8 $ q[7:0] $end
$upscope $end
$upscope $end
$enddefinitions $end
#0
1!
b00000001 "
1#
b00000001 $
#10000000
0!
0#
#20000000
1!
b00000010 "
1#
b00000010 $
#30000000
0!
0#
#40000000
1!
b00000011 "
1#
b00000011 $
#50000000
0!
0#
#60000000
1!
b00000100 "
1#
b00000100 $
#70000000
0!
0#
#80000000
1!
b00000101 "
1#
b00000101 $
#90000000
0!
0#
#100000000
1!
b00000110 "
1#
b00000110 $
#110000000
0!
0#
#120000000
1!
b00000111 "
1#
b00000111 $
#130000000
0!
0#
#140000000
1!
b00001000 "
1#
b00001000 $
#150000000
0!
0#
#160000000
1!
b00001001 "
1#
b00001001 $
#170000000
0!
0#
#180000000
1!
b00001010 "
1#
b00001010 $
#190000000
0!
0#
#200000000
1!
b00001011 "
1#
b00001011 $
#210000000
0!
0#
#220000000
1!
b00001100 "
1#
b00001100 $
#230000000
0!
0#
#240000000
1!
b00001101 "
1#
b00001101 $
#250000000
0!
0#
#260000000
1!
b00001110 "
1#
b00001110 $
#270000000
0!
0#
#280000000
1!
b00001111 "
1#
b00001111 $
#290000000
0!
0#
#300000000
1!
b00010000 "
1#
b00010000 $
#310000000
0!
0#
#320000000
1!
b00010001 "
1#
b00010001 $
#330000000
0!
0#
#340000000
1!
b00010010 "
1#
b00010010 $
#350000000
0!
0#
#360000000
1!
b00010011 "
1#
b00010011 $
#370000000
0!
0#
#380000000
1!
b00010100 "
1#
b00010100 $
#390000000
0!
0#
#400000000
1!
b00010101 "
1#
b00010101 $
#410000000
0!
0#
#420000000
1!
b00010110 "
1#
b00010110 $
#430000000
0!
0#
#440000000
1!
b00010111 "
1#
b00010111 $
#450000000
0!
0#
#460000000
1!
b00011000 "
1#
b00011000 $
#470000000
0!
0#
#480000000
1!
b00011001 "
1#
b00011001 $
#490000000
0!
0#
#500000000
1!
b00011010 "
1#
b00011010 $
#510000000
0!
0#
#520000000
1!
b00011011 "
1#
b00011011 $
#530000000
0!
0#
#540000000
1!
b00011100 "
1#
b00011100 $
#550000000
0!
0#
#560000000
1!
b00011101 "
1#
b00011101 $
#570000000
0!
0#
#580000000
1!
b00011110 "
1#
b00011110 $
#590000000
0!
0#
#600000000
1!
b00011111 "
1#
b00011111 $
#610000000
0!
0#
#620000000
1!
b00100000 "
1#
b00100000 $
#630000000
0!
0#
#640000000
1!
b00100001 "
1#
b00100001 $
#650000000
0!
0#
#660000000
1!
b00100010 "
1#
b00100010 $
#670000000
0!
0#
#680000000
1!
b00100011 "
1#
b00100011 $
#690000000
0!
0#
#700000000
1!
b00100100 "
1#
b00100100 $
#710000000
0!
0#
#720000000
1!
b00100101 "
1#
b00100101 $
#730000000
0!
0#
#740000000
1!
b00100110 "
1#
b00100110 $
#750000000
0!
0#
#760000000
1!
b00100111 "
1#
b00100111 $
#770000000
0!
0#
#780000000
1!
b00101000 "
1#
b00101000 $
#790000000
0!
0#
#800000000
1!
b00101001 "
1#
b00101001 $
#810000000
0!
0#
#820000000
1!
b00101010 "
1#
b00101010 $
#830000000
0!
0#
#840000000
1!
b00101011 "
1#
b00101011 $
#850000000
0!
0#
#860000000
1!
b00101100 "
1#
b00101100 $
#870000000
0!
0#
#880000000
1!
b00101101 "
1#
b00101101 $
#890000000
0!
0#
#900000000
1!
b00101110 "
1#
b00101110 $
#910000000
0!
0#
#920000000
1!
b00101111 "
1#
b00101111 $
#930000000
0!
0#
#940000000
1!
b00110000 "
1#
b00110000 $
#950000000
0!
0#
#960000000
1!
b00110001 "
1#
b00110001 $
#970000000
0!
0#
#980000000
1!
b00110010 "
1#
b00110010 $
#990000000
0!
0#
#1000000000
1!
b00110011 "
1#
b00110011 $
#1010000000
0!
0#
#1020000000
1!
b00110100 "
1#
b00110100 $
#1030000000
0!
0#
#1040000000
1!
b00110101 "
1#
b00110101 $
#1050000000
0!
0#
#1060000000
1!
b00110110 "
1#
b00110110 $
#1070000000
0!
0#
#1080000000
1!
b00110111 "
1#
b00110111 $
#1090000000
0!
0#
#1100000000
1!
b00111000 "
1#
b00111000 $
#1110000000
0!
0#
#1120000000
1!
b00111001 "
1#
b00111001 $
#1130000000
0!
0#
#1140000000
1!
b00111010 "
1#
b00111010 $
#1150000000
0!
0#
#1160000000
1!
b00111011 "
1#
b00111011 $
#1170000000
0!
0#
#1180000000
1!
b00111100 "
1#
b00111100 $
#1190000000
0!
0#
#1200000000
1!
b00111101 "
1#
b00111101 $
#1210000000
0!
0#
#1220000000
1!
b00111110 "
1#
b00111110 $
#1230000000
0!
0#
#1240000000
1!
b00111111 "
1#
b00111111 $
#1250000000
0!
0#
#1260000000
1!
b01000000 "
1#
b01000000 $
#1270000000
0!
0#
#1280000000
1!
b01000001 "
1#
b01000001 $
#1290000000
0!
0#
#1300000000
1!
b01000010 "
1#
b01000010 $
#1310000000
0!
0#
#1320000000
1!
b01000011 "
1#
b01000011 $
#1330000000
0!
0#
#1340000000
1!
b01000100 "
1#
b01000100 $
#1350000000
0!
0#
#1360000000
1!
b01000101 "
1#
b01000101 $
#1370000000
0!
0#
#1380000000
1!
b01000110 "
1#
b01000110 $
#1390000000
0!
0#
#1400000000
1!
b01000111 "
1#
b01000111 $
#1410000000
0!
0#
#1420000000
1!
b01001000 "
1#
b01001000 $
#1430000000
0!
0#
#1440000000
1!
b01001001 "
1#
b01001001 $
#1450000000
0!
0#
#1460000000
1!
b01001010 "
1#
b01001010 $
#1470000000
0!
0#
#1480000000
1!
b01001011 "
1#
b01001011 $
#1490000000
0!
0#
#1500000000
1!
b01001100 "
1#
b01001100 $
#1510000000
0!
0#
#1520000000
1!
b01001101 "
1#
b01001101 $
#1530000000
0!
0#
#1540000000
1!
b01001110 "
1#
b01001110 $
#1550000000
0!
0#
#1560000000
1!
b01001111 "
1#
b01001111 $
#1570000000
0!
0#
#1580000000
1!
b01010000 "
1#
b01010000 $
#1590000000
0!
0#
#1600000000
1!
b01010001 "
1#
b01010001 $
#1610000000
0!
0#
#1620000000
1!
b01010010 "
1#
b01010010 $
#1630000000
0!
0#
#1640000000
1!
b01010011 "
1#
b01010011 $
#1650000000
0!
0#
#1660000000
1!
b01010100 "
1#
b01010100 $
#1670000000
0!
0#
#1680000000
1!
b01010101 "
1#
b01010101 $
#1690000000
0!
0#
#1700000000
1!
b01010110 "
1#
b01010110 $
#1710000000
0!
0#
#1720000000
1!
b01010111 "
1#
b01010111 $
#1730000000
0!
0#
#1740000000
1!
b01011000 "
1#
b01011000 $
#1750000000
0!
0#
#1760000000
1!
b01011001 "
1#
b01011001 $
#1770000000
0!
0#
#1780000000
1!
b01011010 "
1#
b01011010 $
#1790000000
0!
0#
#1800000000
1!
b01011011 "
1#
b01011011 $
#1810000000
0!
0#
#1820000000
1!
b01011100 "
1#
b01011100 $
#1830000000
0!
0#
#1840000000
1!
b01011101 "
1#
b01011101 $
#1850000000
0!
0#
#1860000000
1!
b01011110 "
1#
b01011110 $
#1870000000
0!
0#
#1880000000
1!
b01011111 "
1#
b01011111 $
#1890000000
0!
0#
#1900000000
1!
b01100000 "
1#
b01100000 $
#1910000000
0!
0#
#1920000000
1!
b01100001 "
1#
b01100001 $
#1930000000
0!
0#
#1940000000
1!
b01100010 "
1#
b01100010 $
#1950000000
0!
0#
#1960000000
1!
b01100011 "
1#
b01100011 $
#1970000000
0!
0#
#1980000000
1!
b01100100 "
1#
b01100100 $
#1990000000
0!
0#
#2000000000
1!
b01100101 "
1#
b01100101 $
#2010000000
0!
0#
#2020000000
1!
b01100110 "
1#
b01100110 $
#2030000000
0!
0#
#2040000000
1!
b01100111 "
1#
b01100111 $
#2050000000
0!
0#
#2060000000
1!
b01101000 "
1#
b01101000 $
#2070000000
0!
0#
#2080000000
1!
b01101001 "
1#
b01101001 $
#2090000000
0!
0#
#2100000000
1!
b01101010 "
1#
b01101010 $
#2110000000
0!
0#
#2120000000
1!
b01101011 "
1#
b01101011 $
#2130000000
0!
0#
#2140000000
1!
b01101100 "
1#
b01101100 $
#2150000000
0!
0#
#2160000000
1!
b01101101 "
1#
b01101101 $
#2170000000
0!
0#
#2180000000
1!
b01101110 "
1#
b01101110 $
#2190000000
0!
0#
#2200000000
1!
b01101111 "
1#
b01101111 $
#2210000000
0!
0#
#2220000000
1!
b01110000 "
1#
b01110000 $
#2230000000
0!
0#
#2240000000
1!
b01110001 "
1#
b01110001 $
#2250000000
0!
0#
#2260000000
1!
b01110010 "
1#
b01110010 $
#2270000000
0!
0#
#2280000000
1!
b01110011 "
1#
b01110011 $
#2290000000
0!
0#
#2300000000
1!
b01110100 "
1#
b01110100 $
#2310000000
0!
0#
#2320000000
1!
b01110101 "
1#
b01110101 $
#2330000000
0!
0#
#2340000000
1!
b01110110 "
1#
b01110110 $
#2350000000
0!
0#
#2360000000
1!
b01110111 "
1#
b01110111 $
#2370000000
0!
0#
#2380000000
1!
b01111000 "
1#
b01111000 $
#2390000000
0!
0#
#2400000000
1!
b01111001 "
1#
b01111001 $
#2410000000
0!
0#
#2420000000
1!
b01111010 "
1#
b01111010 $
#2430000000
0!
0#
#2440000000
1!
b01111011 "
1#
b01111011 $
#2450000000
0!
0#
#2460000000
1!
b01111100 "
1#
b01111100 $
#2470000000
0!
0#
#2480000000
1!
b01111101 "
1#
b01111101 $
#2490000000
0!
0#
#2500000000
1!
b01111110 "
1#
b01111110 $
#2510000000
0!
0#
#2520000000
1!
b01111111 "
1#
b01111111 $
#2530000000
0!
0#
#2540000000
1!
b10000000 "
1#
b10000000 $
#2550000000
0!
0#
#2560000000
1!
b10000001 "
1#
b10000001 $
#2570000000
0!
0#
#2580000000
1!
b10000010 "
1#
b10000010 $
#2590000000
0!
0#
#2600000000
1!
b10000011 "
1#
b10000011 $
#2610000000
0!
0#
#2620000000
1!
b10000100 "
1#
b10000100 $
#2630000000
0!
0#
#2640000000
1!
b10000101 "
1#
b10000101 $
#2650000000
0!
0#
#2660000000
1!
b10000110 "
1#
b10000110 $
#2670000000
0!
0#
#2680000000
1!
b10000111 "
1#
b10000111 $
#2690000000
0!
0#
#2700000000
1!
b10001000 "
1#
b10001000 $
#2710000000
0!
0#
#2720000000
1!
b10001001 "
1#
b10001001 $
#2730000000
0!
0#
#2740000000
1!
b10001010 "
1#
b10001010 $
#2750000000
0!
0#
#2760000000
1!
b10001011 "
1#
b10001011 $
#2770000000
0!
0#
#2780000000
1!
b10001100 "
1#
b10001100 $
#2790000000
0!
0#
#2800000000
1!
b10001101 "
1#
b10001101 $
#2810000000
0!
0#
#2820000000
1!
b10001110 "
1#
b10001110 $
#2830000000
0!
0#
#2840000000
1!
b10001111 "
1#
b10001111 $
#2850000000
0!
0#
#2860000000
1!
b10010000 "
1#
b10010000 $
#2870000000
0!
0#
#2880000000
1!
b10010001 "
1#
b10010001 $
#2890000000
0!
0#
#2900000000
1!
b10010010 "
1#
b10010010 $
#2910000000
0!
0#
#2920000000
1!
b10010011 "
1#
b10010011 $
#2930000000
0!
0#
#2940000000
1!
b10010100 "
1#
b10010100 $
#2950000000
0!
0#
#2960000000
1!
b10010101 "
1#
b10010101 $
#2970000000
0!
0#
#2980000000
1!
b10010110 "
1#
b10010110 $
#2990000000
0!
0#
#3000000000
1!
b10010111 "
1#
b10010111 $
#3010000000
0!
0#
#3020000000
1!
b10011000 "
1#
b10011000 $
#3030000000
0!
0#
#3040000000
1!
b10011001 "
1#
b10011001 $
#3050000000
0!
0#
#3060000000
1!
b10011010 "
1#
b10011010 $
#3070000000
0!
0#
#3080000000
1!
b10011011 "
1#
b10011011 $
#3090000000
0!
0#
#3100000000
1!
b10011100 "
1#
b10011100 $
#3110000000
0!
0#
#3120000000
1!
b10011101 "
1#
b10011101 $
#3130000000
0!
0#
#3140000000
1!
b10011110 "
1#
b10011110 $
#3150000000
0!
0#
#3160000000
1!
b10011111 "
1#
b10011111 $
#3170000000
0!
0#
#3180000000
1!
b10100000 "
1#
b10100000 $
#3190000000
0!
0#
#3200000000
1!
b10100001 "
1#
b10100001 $
#3210000000
0!
0#
#3220000000
1!
b10100010 "
1#
b10100010 $
#3230000000
0!
0#
#3240000000
1!
b10100011 "
1#
b10100011 $
#3250000000
0!
0#
#3260000000
1!
b10100100 "
1#
b10100100 $
#3270000000
0!
0#
#3280000000
1!
b10100101 "
1#
b10100101 $
#3290000000
0!
0#
#3300000000
1!
b10100110 "
1#
b10100110 $
#3310000000
0!
0#
#3320000000
1!
b10100111 "
1#
b10100111 $
#3330000000
0!
0#
#3340000000
1!
b10101000 "
1#
b10101000 $
#3350000000
0!
0#
#3360000000
1!
b10101001 "
1#
b10101001 $
#3370000000
0!
0#
#3380000000
1!
b10101010 "
1#
b10101010 $
#3390000000
0!
0#
#3400000000
1!
b10101011 "
1#
b10101011 $
#3410000000
0!
0#
#3420000000
1!
b10101100 "
1#
b10101100 $
#3430000000
0!
0#
#3440000000
1!
b10101101 "
1#
b10101101 $
#3450000000
0!
0#
#3460000000
1!
b10101110 "
1#
b10101110 $
#3470000000
0!
0#
#3480000000
1!
b10101111 "
1#
b10101111 $
#3490000000
0!
0#
#3500000000
1!
b10110000 "
1#
b10110000 $
#3510000000
0!
0#
#3520000000
1!
b10110001 "
1#
b10110001 $
#3530000000
0!
0#
#3540000000
1!
b10110010 "
1#
b10110010 $
#3550000000
0!
0#
#3560000000
1!
b10110011 "
1#
b10110011 $
#3570000000
0!
0#
#3580000000
1!
b10110100 "
1#
b10110100 $
#3590000000
0!
0#
#3600000000
1!
b10110101 "
1#
b10110101 $
#3610000000
0!
0#
#3620000000
1!
b10110110 "
1#
b10110110 $
#3630000000
0!
0#
#3640000000
1!
b10110111 "
1#
b10110111 $
#3650000000
0!
0#
#3660000000
1!
b10111000 "
1#
b10111000 $
#3670000000
0!
0#
#3680000000
1!
b10111001 "
1#
b10111001 $
#3690000000
0!
0#
#3700000000
1!
b10111010 "
1#
b10111010 $
#3710000000
0!
0#
#3720000000
1!
b10111011 "
1#
b10111011 $
#3730000000
0!
0#
#3740000000
1!
b10111100 "
1#
b10111100 $
#3750000000
0!
0#
#3760000000
1!
b10111101 "
1#
b10111101 $
#3770000000
0!
0#
#3780000000
1!
b10111110 "
1#
b10111110 $
#3790000000
0!
0#
#3800000000
1!
b10111111 "
1#
b10111111 $
#3810000000
0!
0#
#3820000000
1!
b11000000 "
1#
b11000000 $
#3830000000
0!
0#
#3840000000
1!
b11000001 "
1#
b11000001 $
#3850000000
0!
0#
#3860000000
1!
b11000010 "
1#
b11000010 $
#3870000000
0!
0#
#3880000000
1!
b11000011 "
1#
b11000011 $
#3890000000
0!
0#
#3900000000
1!
b11000100 "
1#
b11000100 $
#3910000000
0!
0#
#3920000000
1!
b11000101 "
1#
b11000101 $
#3930000000
0!
0#
#3940000000
1!
b11000110 "
1#
b11000110 $
#3950000000
0!
0#
#3960000000
1!
b11000111 "
1#
b11000111 $
#3970000000
0!
0#
#3980000000
1!
b11001000 "
1#
b11001000 $
#3990000000
0!
0#
#4000000000
1!
b11001001 "
1#
b11001001 $
#4010000000
0!
0#
#4020000000
1!
b11001010 "
1#
b11001010 $
#4030000000
0!
0#
#4040000000
1!
b11001011 "
1#
b11001011 $
#4050000000
0!
0#
#4060000000
1!
b11001100 "
1#
b11001100 $
#4070000000
0!
0#
#4080000000
1!
b11001101 "
1#
b11001101 $
#4090000000
0!
0#
#4100000000
1!
b11001110 "
1#
b11001110 $
#4110000000
0!
0#
#4120000000
1!
b11001111 "
1#
b11001111 $
#4130000000
0!
0#
#4140000000
1!
b11010000 "
1#
b11010000 $
#4150000000
0!
0#
#4160000000
1!
b11010001 "
1#
b11010001 $
#4170000000
0!
0#
#4180000000
1!
b11010010 "
1#
b11010010 $
#4190000000
0!
0#
#4200000000
1!
b11010011 "
1#
b11010011 $
#4210000000
0!
0#
#4220000000
1!
b11010100 "
1#
b11010100 $
#4230000000
0!
0#
#4240000000
1!
b11010101 "
1#
b11010101 $
#4250000000
0!
0#
#4260000000
1!
b11010110 "
1#
b11010110 $
#4270000000
0!
0#
#4280000000
1!
b11010111 "
1#
b11010111 $
#4290000000
0!
0#
#4300000000
1!
b11011000 "
1#
b11011000 $
#4310000000
0!
0#
#4320000000
1!
b11011001 "
1#
b11011001 $
#4330000000
0!
0#
#4340000000
1!
b11011010 "
1#
b11011010 $
#4350000000
0!
0#
#4360000000
1!
b11011011 "
1#
b11011011 $
#4370000000
0!
0#
#4380000000
1!
b11011100 "
1#
b11011100 $
#4390000000
0!
0#
#4400000000
1!
b11011101 "
1#
b11011101 $
#4410000000
0!
0#
#4420000000
1!
b11011110 "
1#
b11011110 $
#4430000000
0!
0#
#4440000000
1!
b11011111 "
1#
b11011111 $
#4450000000
0!
0#
#4460000000
1!
b11100000 "
1#
b11100000 $
#4470000000
0!
0#
#4480000000
1!
b11100001 "
1#
b11100001 $
#4490000000
0!
0#
#4500000000
1!
b11100010 "
1#
b11100010 $
#4510000000
0!
0#
#4520000000
1!
b11100011 "
1#
b11100011 $
#4530000000
0!
0#
#4540000000
1!
b11100100 "
1#
b11100100 $
#4550000000
0!
0#
#4560000000
1!
b11100101 "
1#
b11100101 $
#4570000000
0!
0#
#4580000000
1!
b11100110 "
1#
b11100110 $
#4590000000
0!
0#
#4600000000
1!
b11100111 "
1#
b11100111 $
#4610000000
0!
0#
#4620000000
1!
b11101000 "
1#
b11101000 $
#4630000000
0!
0#
#4640000000
1!
b11101001 "
1#
b11101001 $
#4650000000
0!
0#
#4660000000
1!
b11101010 "
1#
b11101010 $
#4670000000
0!
0#
#4680000000
1!
b11101011 "
1#
b11101011 $
#4690000000
0!
0#
#4700000000
1!
b11101100 "
1#
b11101100 $
#4710000000
0!
0#
#4720000000
1!
b11101101 "
1#
b11101101 $
#4730000000
0!
0#
#4740000000
1!
b11101110 "
1#
b11101110 $
#4750000000
0!
0#
#4760000000
1!
b11101111 "
1#
b11101111 $
#4770000000
0!
0#
#4780000000
1!
b11110000 "
1#
b11110000 $
#4790000000
0!
0#
#4800000000
1!
b11110001 "
1#
b11110001 $
#4810000000
0!
0#
#4820000000
1!
b11110010 "
1#
b11110010 $
#4830000000
0!
0#
#4840000000
1!
b11110011 "
1#
b11110011 $
#4850000000
0!
0#
#4860000000
1!
b11110100 "
1#
b11110100 $
#4870000000
0!
0#
#4880000000
1!
b11110101 "
1#
b11110101 $
#4890000000
0!
0#
#4900000000
1!
b11110110 "
1#
b11110110 $
#4910000000
0!
0#
#4920000000
1!
b11110111 "
1#
b11110111 $
#4930000000
0!
0#
#4940000000
1!
b11111000 "
1#
b11111000 $
#4950000000
0!
0#
#4960000000
1!
b11111001 "
1#
b11111001 $
#4970000000
0!
0#
#4980000000
1!
b11111010 "
1#
b11111010 $
#4990000000
0!
0#
#5000000000
1!
b11111011 "
1#
b11111011 $
#5010000000
0!
0#
#5020000000
1!
b11111100 "
1#
b11111100 $
#5030000000
0!
0#
#5040000000
1!
b11111101 "
1#
b11111101 $
#5050000000
0!
0#
#5060000000
1!
b11111110 "
1#
b11111110 $
#5070000000
0!
0#
#5080000000
1!
b11111111 "
1#
b11111111 $
#5090000000
0!
0#
#5100000000
1!
b11111110 "
1#
b11111110 $
#5110000000
0!
0#
#5120000000
1!
b11111101 "
1#
b11111101 $
#5130000000
0!
0#
#5140000000
1!
b11111100 "
1#
b11111100 $
#5150000000
0!
0#
#5160000000
1!
b11111011 "
1#
b11111011 $
#5170000000
0!
0#
#5180000000
1!
b11111010 "
1#
b11111010 $
#5190000000
0!
0#
#5200000000
1!
b11111001 "
1#
b11111001 $
#5210000000
0!
0#
#5220000000
1!
b11111000 "
1#
b11111000 $
#5230000000
0!
0#
#5240000000
1!
b11110111 "
1#
b11110111 $
#5250000000
0!
0#
#5260000000
1!
b11110110 "
1#
b11110110 $
#5270000000
0!
0#
#5280000000
1!
b11110101 "
1#
b11110101 $
#5290000000
0!
0#
#5300000000
1!
b11110100 "
1#
b11110100 $
#5310000000
0!
0#
#5320000000
1!
b11110011 "
1#
b11110011 $
#5330000000
0!
0#
#5340000000
1!
b11110010 "
1#
b11110010 $
#5350000000
0!
0#
#5360000000
1!
b11110001 "
1#
b11110001 $
#5370000000
0!
0#
#5380000000
1!
b11110000 "
1#
b11110000 $
#5390000000
0!
0#
#5400000000
1!
b11101111 "
1#
b11101111 $
#5410000000
0!
0#
#5420000000
1!
b11101110 "
1#
b11101110 $
#5430000000
0!
0#
#5440000000
1!
b11101101 "
1#
b11101101 $
#5450000000
0!
0#
#5460000000
1!
b11101100 "
1#
b11101100 $
#5470000000
0!
0#
#5480000000
1!
b11101011 "
1#
b11101011 $
#5490000000
0!
0#
#5500000000
1!
b11101010 "
1#
b11101010 $
#5510000000
0!
0#
#5520000000
1!
b11101001 "
1#
b11101001 $
#5530000000
0!
0#
#5540000000
1!
b11101000 "
1#
b11101000 $
#5550000000
0!
0#
#5560000000
1!
b11100111 "
1#
b11100111 $
#5570000000
0!
0#
#5580000000
1!
b11100110 "
1#
b11100110 $
#5590000000
0!
0#
#5600000000
1!
b11100101 "
1#
b11100101 $
#5610000000
0!
0#
#5620000000
1!
b11100100 "
1#
b11100100 $
#5630000000
0!
0#
#5640000000
1!
b11100011 "
1#
b11100011 $
#5650000000
0!
0#
#5660000000
1!
b11100010 "
1#
b11100010 $
#5670000000
0!
0#
#5680000000
1!
b11100001 "
1#
b11100001 $
#5690000000
0!
0#
#5700000000
1!
b11100000 "
1#
b11100000 $
#5710000000
0!
0#
#5720000000
1!
b11011111 "
1#
b11011111 $
#5730000000
0!
0#
#5740000000
1!
b11011110 "
1#
b11011110 $
#5750000000
0!
0#
#5760000000
1!
b11011101 "
1#
b11011101 $
#5770000000
0!
0#
#5780000000
1!
b11011100 "
1#
b11011100 $
#5790000000
0!
0#
#5800000000
1!
b11011011 "
1#
b11011011 $
#5810000000
0!
0#
#5820000000
1!
b11011010 "
1#
b11011010 $
#5830000000
0!
0#
#5840000000
1!
b11011001 "
1#
b11011001 $
#5850000000
0!
0#
#5860000000
1!
b11011000 "
1#
b11011000 $
#5870000000
0!
0#
#5880000000
1!
b11010111 "
1#
b11010111 $
#5890000000
0!
0#
#5900000000
1!
b11010110 "
1#
b11010110 $
#5910000000
0!
0#
#5920000000
1!
b11010101 "
1#
b11010101 $
#5930000000
0!
0#
#5940000000
1!
b11010100 "
1#
b11010100 $
#5950000000
0!
0#
#5960000000
1!
b11010011 "
1#
b11010011 $
#5970000000
0!
0#
#5980000000
1!
b11010010 "
1#
b11010010 $
#5990000000
0!
0#
#6000000000
1!
b11010001 "
1#
b11010001 $
#6010000000
0!
0#
#6020000000
1!
b11010000 "
1#
b11010000 $
#6030000000
0!
0#
#6040000000
1!
b11001111 "
1#
b11001111 $
#6050000000
0!
0#
#6060000000
1!
b11001110 "
1#
b11001110 $
#6070000000
0!
0#
#6080000000
1!
b11001101 "
1#
b11001101 $
#6090000000
0!
0#
#6100000000
1!
b11001100 "
1#
b11001100 $
#6110000000
0!
0#
#6120000000
1!
b11001011 "
1#
b11001011 $
#6130000000
0!
0#
#6140000000
1!
b11001010 "
1#
b11001010 $
#6150000000
0!
0#
#6160000000
1!
b11001001 "
1#
b11001001 $
#6170000000
0!
0#
#6180000000
1!
b11001000 "
1#
b11001000 $
#6190000000
0!
0#
#6200000000
1!
b11000111 "
1#
b11000111 $
#6210000000
0!
0#
#6220000000
1!
b11000110 "
1#
b11000110 $
#6230000000
0!
0#
#6240000000
1!
b11000101 "
1#
b11000101 $
#6250000000
0!
0#
#6260000000
1!
b11000100 "
1#
b11000100 $
#6270000000
0!
0#
#6280000000
1!
b11000011 "
1#
b11000011 $
#6290000000
0!
0#
#6300000000
1!
b11000010 "
1#
b11000010 $
#6310000000
0!
0#
#6320000000
1!
b11000001 "
1#
b11000001 $
#6330000000
0!
0#
#6340000000
1!
b11000000 "
1#
b11000000 $
#6350000000
0!
0#
#6360000000
1!
b10111111 "
1#
b10111111 $
#6370000000
0!
0#
#6380000000
1!
b10111110 "
1#
b10111110 $
#6390000000
0!
0#
#6400000000
1!
b10111101 "
1#
b10111101 $
#6410000000
0!
0#
#6420000000
1!
b10111100 "
1#
b10111100 $
#6430000000
0!
0#
#6440000000
1!
b10111011 "
1#
b10111011 $
#6450000000
0!
0#
#6460000000
1!
b10111010 "
1#
b10111010 $
#6470000000
0!
0#
#6480000000
1!
b10111001 "
1#
b10111001 $
#6490000000
0!
0#
#6500000000
1!
b10111000 "
1#
b10111000 $
#6510000000
0!
0#
#6520000000
1!
b10110111 "
1#
b10110111 $
#6530000000
0!
0#
#6540000000
1!
b10110110 "
1#
b10110110 $
#6550000000
0!
0#
#6560000000
1!
b10110101 "
1#
b10110101 $
#6570000000
0!
0#
#6580000000
1!
b10110100 "
1#
b10110100 $
#6590000000
0!
0#
#6600000000
1!
b10110011 "
1#
b10110011 $
#6610000000
0!
0#
#6620000000
1!
b10110010 "
1#
b10110010 $
#6630000000
0!
0#
#6640000000
1!
b10110001 "
1#
b10110001 $
#6650000000
0!
0#
#6660000000
1!
b10110000 "
1#
b10110000 $
#6670000000
0!
0#
#6680000000
1!
b10101111 "
1#
b10101111 $
#6690000000
0!
0#
#6700000000
1!
b10101110 "
1#
b10101110 $
#6710000000
0!
0#
#6720000000
1!
b10101101 "
1#
b10101101 $
#6730000000
0!
0#
#6740000000
1!
b10101100 "
1#
b10101100 $
#6750000000
0!
0#
#6760000000
1!
b10101011 "
1#
b10101011 $
#6770000000
0!
0#
#6780000000
1!
b10101010 "
1#
b10101010 $
#6790000000
0!
0#
#6800000000
1!
b10101001 "
1#
b10101001 $
#6810000000
0!
0#
#6820000000
1!
b10101000 "
1#
b10101000 $
#6830000000
0!
0#
#6840000000
1!
b10100111 "
1#
b10100111 $
#6850000000
0!
0#
#6860000000
1!
b10100110 "
1#
b10100110 $
#6870000000
0!
0#
#6880000000
1!
b10100101 "
1#
b10100101 $
#6890000000
0!
0#
#6900000000
1!
b10100100 "
1#
b10100100 $
#6910000000
0!
0#
#6920000000
1!
b10100011 "
1#
b10100011 $
#6930000000
0!
0#
#6940000000
1!
b10100010 "
1#
b10100010 $
#6950000000
0!
0#
#6960000000
1!
b10100001 "
1#
b10100001 $
#6970000000
0!
0#
#6980000000
1!
b10100000 "
1#
b10100000 $
#6990000000
0!
0#
#7000000000
1!
b10011111 "
1#
b10011111 $
#7010000000
0!
0#
#7020000000
1!
b10011110 "
1#
b10011110 $
#7030000000
0!
0#
#7040000000
1!
b10011101 "
1#
b10011101 $
#7050000000
0!
0#
#7060000000
1!
b10011100 "
1#
b10011100 $
#7070000000
0!
0#
#7080000000
1!
b10011011 "
1#
b10011011 $
#7090000000
0!
0#
#7100000000
1!
b10011010 "
1#
b10011010 $
#7110000000
0!
0#
#7120000000
1!
b10011001 "
1#
b10011001 $
#7130000000
0!
0#
#7140000000
1!
b10011000 "
1#
b10011000 $
#7150000000
0!
0#
#7160000000
1!
b10010111 "
1#
b10010111 $
#7170000000
0!
0#
#7180000000
1!
b10010110 "
1#
b10010110 $
#7190000000
0!
0#
#7200000000
1!
b10010101 "
1#
b10010101 $
#7210000000
0!
0#
#7220000000
1!
b10010100 "
1#
b10010100 $
#7230000000
0!
0#
#7240000000
1!
b10010011 "
1#
b10010011 $
#7250000000
0!
0#
#7260000000
1!
b10010010 "
1#
b10010010 $
#7270000000
0!
0#
#7280000000
1!
b10010001 "
1#
b10010001 $
#7290000000
0!
0#
#7300000000
1!
b10010000 "
1#
b10010000 $
#7310000000
0!
0#
#7320000000
1!
b10001111 "
1#
b10001111 $
#7330000000
0!
0#
#7340000000
1!
b10001110 "
1#
b10001110 $
