l2/ex5.vhd
library IEEE;
use IEEE.STD_LOGIC_1164.ALL;

entity fixmux_b is
port (
  a,b,c : in bit;
  s0    : in bit;
  x     : out bit
);
end fixmux_b;

architecture fixmux_behav of fixmux_b is
begin
process (a,b,c, s0)
  variable sel: integer;
  begin
    if s0='0' then
	   sel := 0; -- or
	 else
	   sel := 1; -- and
	 end if;
	 case sel is 
	   when 0 =>
		    x <= (a or b or c) or  (a and b and c); -- (a or b or c)
	   when others =>
		    x <= (a or b or c) and (a and b and c); -- (a and b and c)
	 end case;
  end process;
end fixmux_behav;

l2/ex5_tb.vhd
--  A testbench has no ports.
entity fixmux_tb is
end fixmux_tb;

architecture behav of fixmux_tb is
  --  Declaration of the component that will be instantiated.
  component fixmux_b
    port (a, b, c, s0 : in bit; x : out bit);
  end component;

  --  Specifies which entity is bound with the component.
  for fixmux_0: fixmux_b use entity work.fixmux_b;
  signal a, b, c, s0, x : bit;
begin
  --  Component instantiation.
  fixmux_0: fixmux_b port map (a => a, b => b, c => c, s0 => s0, x => x);

  --  This process does the real job.
  process
    type pattern_type is record
      --  The inputs of the fixmux_b.
      a, b, c, s0 : bit;
      --  The expected outputs of the fixmux_b.
      x : bit;
    end record;
    --  The patterns to apply.
    type pattern_array is array (natural range <>) of pattern_type;
    constant patterns : pattern_array :=
      (('0', '0', '0', '0', '0'),
       ('0', '0', '0', '1', '0'),
       ('0', '0', '1', '0', '1'),
       ('0', '0', '1', '1', '0'),
       ('0', '1', '0', '0', '1'),
       ('0', '1', '0', '1', '0'),
       ('0', '1', '1', '0', '1'),
       ('0', '1', '1', '1', '0'),
       ('1', '0', '0', '0', '1'),
       ('1', '0', '0', '1', '0'),
       ('1', '0', '1', '0', '1'),
       ('1', '0', '1', '1', '0'),
       ('1', '1', '0', '0', '1'),
       ('1', '1', '0', '1', '0'),
       ('1', '1', '1', '0', '1'),
       ('1', '1', '1', '1', '1'));      
  begin
    --  Check each pattern.
    for i in patterns'range loop
      --  Set the inputs.
      a <= patterns(i).a;
      b <= patterns(i).b;
      c <= patterns(i).c;
      s0 <= patterns(i).s0;
      --  Wait for the results.
      wait for 1 ns;
      --  Check the outputs.
      assert x = patterns(i).x
        report "bad carry out value" severity error;
    end loop;
    assert false report "end of test" severity note;
    --  Wait forever; this will finish the simulation.
    wait;
  end process;

end behav;

l2/fixmux_tb.vcd
$date
  Tue Apr  6 20:07:57 2021
$end
$version
  GHDL v0
$end
$timescale
  1 fs
$end
$scope module standard $end
$upscope $end
$scope module std_logic_1164 $end
$upscope $end
$scope module fixmux_tb $end
$var reg 1 ! a $end
$var reg 1 " b $end
$var reg 1 # c $end
$var reg 1 $ s0 $end
$var reg 1 % x $end
$scope module fixmux_0 $end
$var reg 1 & a $end
$var reg 1 ' b $end
$var reg 1 ( c $end
$var reg 1 ) s0 $end
$var reg 1 * x $end
$upscope $end
$upscope $end
$enddefinitions $end
#0
0!
0"
0#
0$
0%
0&
0'
0(
0)
0*
#1000000
1$
1)
#2000000
1#
0$
1%
1(
0)
1*
#3000000
1$
0%
1)
0*
#4000000
1"
0#
0$
1%
1'
0(
0)
1*
#5000000
1$
0%
1)
0*
#6000000
1#
0$
1%
1(
0)
1*
#7000000
1$
0%
1)
0*
#8000000
1!
0"
0#
0$
1%
1&
0'
0(
0)
1*
#9000000
1$
0%
1)
0*
#10000000
1#
0$
1%
1(
0)
1*
#11000000
1$
0%
1)
0*
#12000000
1"
0#
0$
1%
1'
0(
0)
1*
#13000000
1$
0%
1)
0*
#14000000
1#
0$
1%
1(
0)
1*
#15000000
1$
1)
